{"annotations": [{"area": null, "bbox": [], "category_id": "009", "id": "00065", "image_id": "00224", "iscrowd": null, "segmentation": [[124, 130, 161, 156, 172, 98]]}], "categories": [{"id": "009", "name": "unknown", "supercategory": null}], "images": [{"coco_url": "https://s3-eu-west-1.amazonaws.com/viae-image-annotator/in_progress_data/images/00224-fashion.jpeg", "date_captured": null, "file_name": "00224-fashion.jpeg", "flickr_url": "https://s3-eu-west-1.amazonaws.com/viae-image-annotator/in_progress_data/images/00224-fashion.jpeg", "height": null, "id": "00224", "license": null, "size": 9511, "width": null}], "info": {"contributor": null, "date_created": "2019-05-29T18:53:18.860925", "description": null, "url": null, "version": null, "year": 2019}, "licenses": [{"id": null, "name": null, "url": null}]}